temporalvoicesdk-0.1.0.dist-info/licenses/LICENSE
voice_analytics/__init__.py
voice_analytics/models.py
voice_analytics/processor.py
voice_analytics/realtime_analyzer.py
voice_analytics/visualizer.py
temporalvoicesdk-0.1.0.dist-info/METADATA
temporalvoicesdk-0.1.0.dist-info/WHEEL
temporalvoicesdk-0.1.0.dist-info/top_level.txt
temporalvoicesdk-0.1.0.dist-info/RECORD
