Metadata-Version: 2.4
Name: temporalvoicesdk
Version: 0.1.0
Summary: Temporal Voice SDK - Advanced voice analytics and recognition
Home-page: https://github.com/TemporalAITech/TemporalVoiceSDK
Author: Temporal AI Technologies Inc.
Author-email: "Temporal AI Technologies Inc." <support@temporalaitechnologies.com>
License: # Temporal AI Technologies Inc. Proprietary License
Requires-Python: >=3.8
License-File: LICENSE
Requires-Dist: numpy
Requires-Dist: pandas
Requires-Dist: plotly
Requires-Dist: speechrecognition
Dynamic: author
Dynamic: home-page
Dynamic: license-file
Dynamic: requires-python
